{
  "makes": [
    {
      "make": "Toyota",
      "models": ["Camry", "Corolla", "RAV4", "Highlander", "Tacoma", "Prius"]
    },
    {
      "make": "Honda",
      "models": ["Civic", "Accord", "CR-V", "Pilot", "Fit", "HR-V"]
    },
    {
      "make": "Ford",
      "models": ["F-150", "Mustang", "Explorer", "Escape", "Edge", "Focus"]
    },
    {
      "make": "Chevrolet",
      "models": ["Silverado", "Malibu", "Equinox", "Traverse", "Camaro", "Tahoe"]
    },
    {
      "make": "BMW",
      "models": ["3 Series", "5 Series", "X3", "X5", "M3", "7 Series"]
    },
    {
      "make": "Tesla",
      "models": ["Model S", "Model 3", "Model X", "Model Y", "Cybertruck"]
    }
  ]
}
